alanapy/__init__.py
alanapy-0.3.dist-info/LICENSE
alanapy-0.3.dist-info/METADATA
alanapy-0.3.dist-info/WHEEL
alanapy-0.3.dist-info/top_level.txt
alanapy-0.3.dist-info/RECORD
